odoo/addons/stock_location_address_purchase/README.rst
odoo/addons/stock_location_address_purchase/__init__.py
odoo/addons/stock_location_address_purchase/__manifest__.py
odoo/addons/stock_location_address_purchase/i18n/it.po
odoo/addons/stock_location_address_purchase/i18n/stock_location_address_purchase.pot
odoo/addons/stock_location_address_purchase/models/__init__.py
odoo/addons/stock_location_address_purchase/models/purchase.py
odoo/addons/stock_location_address_purchase/models/stock_rule.py
odoo/addons/stock_location_address_purchase/readme/CONTRIBUTORS.md
odoo/addons/stock_location_address_purchase/static/description/icon.png
odoo/addons/stock_location_address_purchase/tests/__init__.py
odoo/addons/stock_location_address_purchase/tests/test_purchase_address.py
odoo/addons/stock_location_address_purchase/tests/test_purchase_buy_rule.py
odoo_addon_stock_location_address_purchase-18.0.1.0.0.1.dist-info/METADATA
odoo_addon_stock_location_address_purchase-18.0.1.0.0.1.dist-info/WHEEL
odoo_addon_stock_location_address_purchase-18.0.1.0.0.1.dist-info/top_level.txt
odoo_addon_stock_location_address_purchase-18.0.1.0.0.1.dist-info/RECORD
