Metadata-Version: 2.1
Name: odoo-addon-stock_location_address_purchase
Version: 18.0.1.0.0.1
Requires-Python: >=3.10
Requires-Dist: odoo-addon-stock_location_address==18.0.*
Requires-Dist: odoo==18.0.*
Summary: Uses the location address on purchases
Home-page: https://github.com/OCA/stock-logistics-transport
License: AGPL-3
Author: Creu Blanca, Odoo Community Association (OCA)
Author-email: support@odoo-community.org
Classifier: Programming Language :: Python
Classifier: Framework :: Odoo
Classifier: Framework :: Odoo :: 18.0
Classifier: License :: OSI Approved :: GNU Affero General Public License v3
